LICENSE.txt
MANIFEST.in
README.md
setup.cfg
setup.py
nearmiss/__init__.py
nearmiss/core.py
nearmiss.egg-info/PKG-INFO
nearmiss.egg-info/SOURCES.txt
nearmiss.egg-info/dependency_links.txt
nearmiss.egg-info/requires.txt
nearmiss.egg-info/top_level.txt
nearmiss/test/__init__.py
nearmiss/test/test_core.py
source/sais.c
source/sais.h
source/tree.c