Metadata-Version: 2.1
Name: nearmiss
Version: 0.1.4
Summary: Fast inexact text searching with suffix arrays
Author: Simon Shaw
Author-email: packaging@secondarymetabolites.org
License: GPLv3+
Classifier: Programming Language :: Python
Classifier: Programming Language :: Python :: 3
Classifier: Development Status :: 3 - Alpha
Classifier: Intended Audience :: Science/Research
Classifier: Topic :: Scientific/Engineering :: Bio-Informatics
Classifier: License :: OSI Approved :: GNU General Public License v3 or later (GPLv3+)
Requires-Python: >=3.9
License-File: LICENSE.txt
Provides-Extra: testing
Requires-Dist: pytest>=3.3.0; extra == "testing"
Requires-Dist: coverage; extra == "testing"
